<annotation>
	<folder>images</folder>
	<filename>10.PNG</filename>
	<path>C:\Users\delaney\Desktop\capstone\images\10.PNG</path>
	<source>
		<database>Unknown</database>
	</source>
	<size>
		<width>1260</width>
		<height>1523</height>
		<depth>3</depth>
	</size>
	<segmented>0</segmented>
	<object>
		<name>textline</name>
		<pose>Unspecified</pose>
		<truncated>0</truncated>
		<difficult>0</difficult>
		<bndbox>
			<xmin>531</xmin>
			<ymin>157</ymin>
			<xmax>1129</xmax>
			<ymax>219</ymax>
		</bndbox>
	</object>
	<object>
		<name>textline</name>
		<pose>Unspecified</pose>
		<truncated>0</truncated>
		<difficult>0</difficult>
		<bndbox>
			<xmin>140</xmin>
			<ymin>997</ymin>
			<xmax>1176</xmax>
			<ymax>1066</ymax>
		</bndbox>
	</object>
	<object>
		<name>textline</name>
		<pose>Unspecified</pose>
		<truncated>0</truncated>
		<difficult>0</difficult>
		<bndbox>
			<xmin>61</xmin>
			<ymin>1200</ymin>
			<xmax>674</xmax>
			<ymax>1260</ymax>
		</bndbox>
	</object>
	<object>
		<name>textline</name>
		<pose>Unspecified</pose>
		<truncated>0</truncated>
		<difficult>0</difficult>
		<bndbox>
			<xmin>742</xmin>
			<ymin>1198</ymin>
			<xmax>1178</xmax>
			<ymax>1261</ymax>
		</bndbox>
	</object>
	<object>
		<name>textline</name>
		<pose>Unspecified</pose>
		<truncated>0</truncated>
		<difficult>0</difficult>
		<bndbox>
			<xmin>745</xmin>
			<ymin>1332</ymin>
			<xmax>1178</xmax>
			<ymax>1393</ymax>
		</bndbox>
	</object>
	<object>
		<name>textline</name>
		<pose>Unspecified</pose>
		<truncated>0</truncated>
		<difficult>0</difficult>
		<bndbox>
			<xmin>62</xmin>
			<ymin>1330</ymin>
			<xmax>676</xmax>
			<ymax>1396</ymax>
		</bndbox>
	</object>
</annotation>
