<annotation>
	<folder>images</folder>
	<filename>144.png</filename>
	<path>D:\Documents\ASU\Classes\CSE 485\FormDataset\data\images\144.png</path>
	<source>
		<database>Unknown</database>
	</source>
	<size>
		<width>754</width>
		<height>1000</height>
		<depth>1</depth>
	</size>
	<segmented>0</segmented>
	<object>
		<name>textline</name>
		<pose>Unspecified</pose>
		<truncated>0</truncated>
		<difficult>0</difficult>
		<bndbox>
			<xmin>219</xmin>
			<ymin>374</ymin>
			<xmax>620</xmax>
			<ymax>389</ymax>
		</bndbox>
	</object>
	<object>
		<name>textline</name>
		<pose>Unspecified</pose>
		<truncated>0</truncated>
		<difficult>0</difficult>
		<bndbox>
			<xmin>244</xmin>
			<ymin>405</ymin>
			<xmax>620</xmax>
			<ymax>419</ymax>
		</bndbox>
	</object>
	<object>
		<name>textline</name>
		<pose>Unspecified</pose>
		<truncated>0</truncated>
		<difficult>0</difficult>
		<bndbox>
			<xmin>217</xmin>
			<ymin>434</ymin>
			<xmax>620</xmax>
			<ymax>448</ymax>
		</bndbox>
	</object>
	<object>
		<name>textline</name>
		<pose>Unspecified</pose>
		<truncated>0</truncated>
		<difficult>0</difficult>
		<bndbox>
			<xmin>242</xmin>
			<ymin>536</ymin>
			<xmax>620</xmax>
			<ymax>550</ymax>
		</bndbox>
	</object>
	<object>
		<name>textline</name>
		<pose>Unspecified</pose>
		<truncated>0</truncated>
		<difficult>0</difficult>
		<bndbox>
			<xmin>256</xmin>
			<ymin>567</ymin>
			<xmax>620</xmax>
			<ymax>581</ymax>
		</bndbox>
	</object>
	<object>
		<name>textline</name>
		<pose>Unspecified</pose>
		<truncated>0</truncated>
		<difficult>0</difficult>
		<bndbox>
			<xmin>333</xmin>
			<ymin>853</ymin>
			<xmax>623</xmax>
			<ymax>865</ymax>
		</bndbox>
	</object>
	<object>
		<name>textline</name>
		<pose>Unspecified</pose>
		<truncated>0</truncated>
		<difficult>0</difficult>
		<bndbox>
			<xmin>237</xmin>
			<ymin>879</ymin>
			<xmax>372</xmax>
			<ymax>893</ymax>
		</bndbox>
	</object>
	<object>
		<name>textline</name>
		<pose>Unspecified</pose>
		<truncated>0</truncated>
		<difficult>0</difficult>
		<bndbox>
			<xmin>484</xmin>
			<ymin>878</ymin>
			<xmax>621</xmax>
			<ymax>893</ymax>
		</bndbox>
	</object>
	<object>
		<name>checkbox</name>
		<pose>Unspecified</pose>
		<truncated>0</truncated>
		<difficult>0</difficult>
		<bndbox>
			<xmin>209</xmin>
			<ymin>686</ymin>
			<xmax>224</xmax>
			<ymax>701</ymax>
		</bndbox>
	</object>
	<object>
		<name>checkbox</name>
		<pose>Unspecified</pose>
		<truncated>0</truncated>
		<difficult>0</difficult>
		<bndbox>
			<xmin>209</xmin>
			<ymin>716</ymin>
			<xmax>224</xmax>
			<ymax>731</ymax>
		</bndbox>
	</object>
	<object>
		<name>checkbox</name>
		<pose>Unspecified</pose>
		<truncated>0</truncated>
		<difficult>0</difficult>
		<bndbox>
			<xmin>209</xmin>
			<ymin>746</ymin>
			<xmax>224</xmax>
			<ymax>761</ymax>
		</bndbox>
	</object>
	<object>
		<name>checkbox</name>
		<pose>Unspecified</pose>
		<truncated>0</truncated>
		<difficult>0</difficult>
		<bndbox>
			<xmin>451</xmin>
			<ymin>746</ymin>
			<xmax>466</xmax>
			<ymax>761</ymax>
		</bndbox>
	</object>
	<object>
		<name>checkbox</name>
		<pose>Unspecified</pose>
		<truncated>0</truncated>
		<difficult>0</difficult>
		<bndbox>
			<xmin>451</xmin>
			<ymin>716</ymin>
			<xmax>466</xmax>
			<ymax>731</ymax>
		</bndbox>
	</object>
	<object>
		<name>checkbox</name>
		<pose>Unspecified</pose>
		<truncated>0</truncated>
		<difficult>0</difficult>
		<bndbox>
			<xmin>451</xmin>
			<ymin>686</ymin>
			<xmax>466</xmax>
			<ymax>701</ymax>
		</bndbox>
	</object>
</annotation>
