<annotations><filename>298.png</filename><folder>images</folder><size><width>815</width><height>1024</height><depth>3</depth></size><object><name /><pose>Unspecified</pose><truncated>0</truncated><difficult>0</difficult><bndbox><xmin>324.9995875</xmin><ymin>57.000448000000006</ymin><xmax>667.9996725000001</xmax><ymax>84.00025600000001</ymax></bndbox></object><object><name /><pose>Unspecified</pose><truncated>0</truncated><difficult>0</difficult><bndbox><xmin>324.999995</xmin><ymin>95.000576</ymin><xmax>663.000055</xmax><ymax>124.00025600000001</ymax></bndbox></object><object><name /><pose>Unspecified</pose><truncated>0</truncated><difficult>0</difficult><bndbox><xmin>324.99958749999996</xmin><ymin>132.00025599999998</ymin><xmax>663.9996524999999</xmax><ymax>162.000384</ymax></bndbox></object><object><name /><pose>Unspecified</pose><truncated>0</truncated><difficult>0</difficult><bndbox><xmin>324.999995</xmin><ymin>169.99936</ymin><xmax>665.000065</xmax><ymax>193.999872</ymax></bndbox></object><object><name /><pose>Unspecified</pose><truncated>0</truncated><difficult>0</difficult><bndbox><xmin>324.999995</xmin><ymin>202.999808</ymin><xmax>665.000065</xmax><ymax>234.999808</ymax></bndbox></object><object><name /><pose>Unspecified</pose><truncated>0</truncated><difficult>0</difficult><bndbox><xmin>34.99976749999999</xmin><ymin>262.00064</ymin><xmax>140.9994825</xmax><ymax>291.00032</ymax></bndbox></object><object><name /><pose>Unspecified</pose><truncated>0</truncated><difficult>0</difficult><bndbox><xmin>251.00003250000003</xmin><ymin>242.99980799999997</ymin><xmax>406.9999975</xmax><ymax>269.999616</ymax></bndbox></object><object><name /><pose>Unspecified</pose><truncated>0</truncated><difficult>0</difficult><bndbox><xmin>429.0001075</xmin><ymin>244.99967999999998</ymin><xmax>468.0003025</xmax><ymax>271.000064</ymax></bndbox></object><object><name /><pose>Unspecified</pose><truncated>0</truncated><difficult>0</difficult><bndbox><xmin>348.00011</xmin><ymin>266.99980800000003</ymin><xmax>384.00029</xmax><ymax>288.0</ymax></bndbox></object><object><name /><pose>Unspecified</pose><truncated>0</truncated><difficult>0</difficult><bndbox><xmin>10.999647499999952</xmin><ymin>301.000192</ymin><xmax>486.9995825</xmax><ymax>324.000256</ymax></bndbox></object><object><name /><pose>Unspecified</pose><truncated>0</truncated><difficult>0</difficult><bndbox><xmin>674.9997075000001</xmin><ymin>355.00032</ymin><xmax>709.9998825</xmax><ymax>380.00025600000004</ymax></bndbox></object><object><name /><pose>Unspecified</pose><truncated>0</truncated><difficult>0</difficult><bndbox><xmin>88.00003249999999</xmin><ymin>374.999552</ymin><xmax>119.0001875</xmax><ymax>400.99993600000005</ymax></bndbox></object><object><name /><pose>Unspecified</pose><truncated>0</truncated><difficult>0</difficult><bndbox><xmin>154.99996</xmin><ymin>370.000384</ymin><xmax>299.99987</xmax><ymax>400.999936</ymax></bndbox></object><object><name /><pose>Unspecified</pose><truncated>0</truncated><difficult>0</difficult><bndbox><xmin>327.9996025</xmin><ymin>376.999936</ymin><xmax>368.99980750000003</xmax><ymax>401.99987200000004</ymax></bndbox></object><object><name /><pose>Unspecified</pose><truncated>0</truncated><difficult>0</difficult><bndbox><xmin>556.000335</xmin><ymin>408.999424</ymin><xmax>697.000225</xmax><ymax>434.99980800000003</ymax></bndbox></object><object><name /><pose>Unspecified</pose><truncated>0</truncated><difficult>0</difficult><bndbox><xmin>122.00020250000001</xmin><ymin>632.0005120000001</ymin><xmax>241.99998750000003</xmax><ymax>657.000448</ymax></bndbox></object><object><name /><pose>Unspecified</pose><truncated>0</truncated><difficult>0</difficult><bndbox><xmin>482.0003725</xmin><ymin>615.000576</ymin><xmax>596.0001275000001</xmax><ymax>642.000384</ymax></bndbox></object><object><name /><pose>Unspecified</pose><truncated>0</truncated><difficult>0</difficult><bndbox><xmin>339.0004725</xmin><ymin>629.999616</ymin><xmax>469.00030749999996</xmax><ymax>664.999936</ymax></bndbox></object><object><name /><pose>Unspecified</pose><truncated>0</truncated><difficult>0</difficult><bndbox><xmin>7.00044250000002</xmin><ymin>724.000256</ymin><xmax>787.0002675000001</xmax><ymax>751.0000640000001</ymax></bndbox></object><object><name /><pose>Unspecified</pose><truncated>0</truncated><difficult>0</difficult><bndbox><xmin>116.00058000000001</xmin><ymin>761.9993599999999</ymin><xmax>207.00022</xmax><ymax>785.999872</ymax></bndbox></object><object><name /><pose>Unspecified</pose><truncated>0</truncated><difficult>0</difficult><bndbox><xmin>95.99966500000005</xmin><ymin>891.999744</ymin><xmax>793.999895</xmax><ymax>918.999552</ymax></bndbox></object><object><name /><pose>Unspecified</pose><truncated>0</truncated><difficult>0</difficult><bndbox><xmin>180.9996825</xmin><ymin>929.999872</ymin><xmax>213.9998475</xmax><ymax>951.000064</ymax></bndbox></object><object><name /><pose>Unspecified</pose><truncated>0</truncated><difficult>0</difficult><bndbox><xmin>258.00006749999994</xmin><ymin>929.999872</ymin><xmax>283.00019249999997</xmax><ymax>954.000384</ymax></bndbox></object><object><name /><pose>Unspecified</pose><truncated>0</truncated><difficult>0</difficult><bndbox><xmin>238.00037500000002</xmin><ymin>945.9998720000001</ymin><xmax>339.000065</xmax><ymax>974.999552</ymax></bndbox></object></annotations>