<annotation>
	<folder>images</folder>
	<filename>133.png</filename>
	<path>D:\Documents\ASU\Classes\CSE 485\FormDataset\data\images\133.png</path>
	<source>
		<database>Unknown</database>
	</source>
	<size>
		<width>334</width>
		<height>416</height>
		<depth>1</depth>
	</size>
	<segmented>0</segmented>
	<object>
		<name>textline</name>
		<pose>Unspecified</pose>
		<truncated>0</truncated>
		<difficult>0</difficult>
		<bndbox>
			<xmin>77</xmin>
			<ymin>59</ymin>
			<xmax>232</xmax>
			<ymax>66</ymax>
		</bndbox>
	</object>
	<object>
		<name>textline</name>
		<pose>Unspecified</pose>
		<truncated>0</truncated>
		<difficult>0</difficult>
		<bndbox>
			<xmin>77</xmin>
			<ymin>81</ymin>
			<xmax>180</xmax>
			<ymax>88</ymax>
		</bndbox>
	</object>
	<object>
		<name>textline</name>
		<pose>Unspecified</pose>
		<truncated>0</truncated>
		<difficult>0</difficult>
		<bndbox>
			<xmin>77</xmin>
			<ymin>108</ymin>
			<xmax>231</xmax>
			<ymax>116</ymax>
		</bndbox>
	</object>
	<object>
		<name>textline</name>
		<pose>Unspecified</pose>
		<truncated>0</truncated>
		<difficult>0</difficult>
		<bndbox>
			<xmin>77</xmin>
			<ymin>129</ymin>
			<xmax>231</xmax>
			<ymax>137</ymax>
		</bndbox>
	</object>
	<object>
		<name>textline</name>
		<pose>Unspecified</pose>
		<truncated>0</truncated>
		<difficult>0</difficult>
		<bndbox>
			<xmin>77</xmin>
			<ymin>151</ymin>
			<xmax>231</xmax>
			<ymax>158</ymax>
		</bndbox>
	</object>
	<object>
		<name>textline</name>
		<pose>Unspecified</pose>
		<truncated>0</truncated>
		<difficult>0</difficult>
		<bndbox>
			<xmin>77</xmin>
			<ymin>174</ymin>
			<xmax>281</xmax>
			<ymax>181</ymax>
		</bndbox>
	</object>
	<object>
		<name>textline</name>
		<pose>Unspecified</pose>
		<truncated>0</truncated>
		<difficult>0</difficult>
		<bndbox>
			<xmin>28</xmin>
			<ymin>183</ymin>
			<xmax>281</xmax>
			<ymax>191</ymax>
		</bndbox>
	</object>
	<object>
		<name>textline</name>
		<pose>Unspecified</pose>
		<truncated>0</truncated>
		<difficult>0</difficult>
		<bndbox>
			<xmin>28</xmin>
			<ymin>192</ymin>
			<xmax>281</xmax>
			<ymax>201</ymax>
		</bndbox>
	</object>
	<object>
		<name>textline</name>
		<pose>Unspecified</pose>
		<truncated>0</truncated>
		<difficult>0</difficult>
		<bndbox>
			<xmin>28</xmin>
			<ymin>202</ymin>
			<xmax>281</xmax>
			<ymax>210</ymax>
		</bndbox>
	</object>
	<object>
		<name>textline</name>
		<pose>Unspecified</pose>
		<truncated>0</truncated>
		<difficult>0</difficult>
		<bndbox>
			<xmin>28</xmin>
			<ymin>212</ymin>
			<xmax>281</xmax>
			<ymax>220</ymax>
		</bndbox>
	</object>
	<object>
		<name>textline</name>
		<pose>Unspecified</pose>
		<truncated>0</truncated>
		<difficult>0</difficult>
		<bndbox>
			<xmin>78</xmin>
			<ymin>229</ymin>
			<xmax>281</xmax>
			<ymax>236</ymax>
		</bndbox>
	</object>
	<object>
		<name>textline</name>
		<pose>Unspecified</pose>
		<truncated>0</truncated>
		<difficult>0</difficult>
		<bndbox>
			<xmin>78</xmin>
			<ymin>251</ymin>
			<xmax>281</xmax>
			<ymax>258</ymax>
		</bndbox>
	</object>
	<object>
		<name>textline</name>
		<pose>Unspecified</pose>
		<truncated>0</truncated>
		<difficult>0</difficult>
		<bndbox>
			<xmin>29</xmin>
			<ymin>260</ymin>
			<xmax>281</xmax>
			<ymax>269</ymax>
		</bndbox>
	</object>
	<object>
		<name>textline</name>
		<pose>Unspecified</pose>
		<truncated>0</truncated>
		<difficult>0</difficult>
		<bndbox>
			<xmin>29</xmin>
			<ymin>270</ymin>
			<xmax>281</xmax>
			<ymax>278</ymax>
		</bndbox>
	</object>
	<object>
		<name>textline</name>
		<pose>Unspecified</pose>
		<truncated>0</truncated>
		<difficult>0</difficult>
		<bndbox>
			<xmin>29</xmin>
			<ymin>280</ymin>
			<xmax>273</xmax>
			<ymax>288</ymax>
		</bndbox>
	</object>
	<object>
		<name>textline</name>
		<pose>Unspecified</pose>
		<truncated>0</truncated>
		<difficult>0</difficult>
		<bndbox>
			<xmin>29</xmin>
			<ymin>290</ymin>
			<xmax>273</xmax>
			<ymax>298</ymax>
		</bndbox>
	</object>
	<object>
		<name>textline</name>
		<pose>Unspecified</pose>
		<truncated>0</truncated>
		<difficult>0</difficult>
		<bndbox>
			<xmin>29</xmin>
			<ymin>300</ymin>
			<xmax>273</xmax>
			<ymax>308</ymax>
		</bndbox>
	</object>
	<object>
		<name>textline</name>
		<pose>Unspecified</pose>
		<truncated>0</truncated>
		<difficult>0</difficult>
		<bndbox>
			<xmin>29</xmin>
			<ymin>310</ymin>
			<xmax>273</xmax>
			<ymax>318</ymax>
		</bndbox>
	</object>
</annotation>