<annotation>
	<folder>images</folder>
	<filename>144.png</filename>
	<path>D:\Documents\ASU\Classes\CSE 485\FormDataset\data\images\144.png</path>
	<source>
		<database>Unknown</database>
	</source>
	<size>
		<width>314</width>
		<height>416</height>
		<depth>1</depth>
	</size>
	<segmented>0</segmented>
	<object>
		<name>textline</name>
		<pose>Unspecified</pose>
		<truncated>0</truncated>
		<difficult>0</difficult>
		<bndbox>
			<xmin>91</xmin>
			<ymin>156</ymin>
			<xmax>258</xmax>
			<ymax>162</ymax>
		</bndbox>
	</object>
	<object>
		<name>textline</name>
		<pose>Unspecified</pose>
		<truncated>0</truncated>
		<difficult>0</difficult>
		<bndbox>
			<xmin>102</xmin>
			<ymin>168</ymin>
			<xmax>258</xmax>
			<ymax>174</ymax>
		</bndbox>
	</object>
	<object>
		<name>textline</name>
		<pose>Unspecified</pose>
		<truncated>0</truncated>
		<difficult>0</difficult>
		<bndbox>
			<xmin>90</xmin>
			<ymin>181</ymin>
			<xmax>258</xmax>
			<ymax>186</ymax>
		</bndbox>
	</object>
	<object>
		<name>textline</name>
		<pose>Unspecified</pose>
		<truncated>0</truncated>
		<difficult>0</difficult>
		<bndbox>
			<xmin>101</xmin>
			<ymin>223</ymin>
			<xmax>258</xmax>
			<ymax>229</ymax>
		</bndbox>
	</object>
	<object>
		<name>textline</name>
		<pose>Unspecified</pose>
		<truncated>0</truncated>
		<difficult>0</difficult>
		<bndbox>
			<xmin>106</xmin>
			<ymin>236</ymin>
			<xmax>258</xmax>
			<ymax>242</ymax>
		</bndbox>
	</object>
	<object>
		<name>textline</name>
		<pose>Unspecified</pose>
		<truncated>0</truncated>
		<difficult>0</difficult>
		<bndbox>
			<xmin>139</xmin>
			<ymin>355</ymin>
			<xmax>259</xmax>
			<ymax>360</ymax>
		</bndbox>
	</object>
	<object>
		<name>textline</name>
		<pose>Unspecified</pose>
		<truncated>0</truncated>
		<difficult>0</difficult>
		<bndbox>
			<xmin>99</xmin>
			<ymin>366</ymin>
			<xmax>155</xmax>
			<ymax>371</ymax>
		</bndbox>
	</object>
	<object>
		<name>textline</name>
		<pose>Unspecified</pose>
		<truncated>0</truncated>
		<difficult>0</difficult>
		<bndbox>
			<xmin>201</xmin>
			<ymin>365</ymin>
			<xmax>258</xmax>
			<ymax>371</ymax>
		</bndbox>
	</object>
	<object>
		<name>checkbox</name>
		<pose>Unspecified</pose>
		<truncated>0</truncated>
		<difficult>0</difficult>
		<bndbox>
			<xmin>87</xmin>
			<ymin>285</ymin>
			<xmax>93</xmax>
			<ymax>292</ymax>
		</bndbox>
	</object>
	<object>
		<name>checkbox</name>
		<pose>Unspecified</pose>
		<truncated>0</truncated>
		<difficult>0</difficult>
		<bndbox>
			<xmin>87</xmin>
			<ymin>298</ymin>
			<xmax>93</xmax>
			<ymax>304</ymax>
		</bndbox>
	</object>
	<object>
		<name>checkbox</name>
		<pose>Unspecified</pose>
		<truncated>0</truncated>
		<difficult>0</difficult>
		<bndbox>
			<xmin>87</xmin>
			<ymin>310</ymin>
			<xmax>93</xmax>
			<ymax>317</ymax>
		</bndbox>
	</object>
	<object>
		<name>checkbox</name>
		<pose>Unspecified</pose>
		<truncated>0</truncated>
		<difficult>0</difficult>
		<bndbox>
			<xmin>188</xmin>
			<ymin>310</ymin>
			<xmax>194</xmax>
			<ymax>317</ymax>
		</bndbox>
	</object>
	<object>
		<name>checkbox</name>
		<pose>Unspecified</pose>
		<truncated>0</truncated>
		<difficult>0</difficult>
		<bndbox>
			<xmin>188</xmin>
			<ymin>298</ymin>
			<xmax>194</xmax>
			<ymax>304</ymax>
		</bndbox>
	</object>
	<object>
		<name>checkbox</name>
		<pose>Unspecified</pose>
		<truncated>0</truncated>
		<difficult>0</difficult>
		<bndbox>
			<xmin>188</xmin>
			<ymin>285</ymin>
			<xmax>194</xmax>
			<ymax>292</ymax>
		</bndbox>
	</object>
</annotation>