<annotation>
	<folder>images</folder>
	<filename>172.png</filename>
	<path>D:\Documents\ASU\Classes\CSE 485\FormDataset\data\images\172.png</path>
	<source>
		<database>Unknown</database>
	</source>
	<size>
		<width>416</width>
		<height>198</height>
		<depth>1</depth>
	</size>
	<segmented>0</segmented>
	<object>
		<name>textline</name>
		<pose>Unspecified</pose>
		<truncated>0</truncated>
		<difficult>0</difficult>
		<bndbox>
			<xmin>10</xmin>
			<ymin>22</ymin>
			<xmax>85</xmax>
			<ymax>31</ymax>
		</bndbox>
	</object>
	<object>
		<name>checkbox</name>
		<pose>Unspecified</pose>
		<truncated>0</truncated>
		<difficult>0</difficult>
		<bndbox>
			<xmin>155</xmin>
			<ymin>21</ymin>
			<xmax>168</xmax>
			<ymax>31</ymax>
		</bndbox>
	</object>
	<object>
		<name>checkbox</name>
		<pose>Unspecified</pose>
		<truncated>0</truncated>
		<difficult>0</difficult>
		<bndbox>
			<xmin>225</xmin>
			<ymin>21</ymin>
			<xmax>238</xmax>
			<ymax>31</ymax>
		</bndbox>
	</object>
	<object>
		<name>checkbox</name>
		<pose>Unspecified</pose>
		<truncated>0</truncated>
		<difficult>0</difficult>
		<bndbox>
			<xmin>280</xmin>
			<ymin>21</ymin>
			<xmax>293</xmax>
			<ymax>31</ymax>
		</bndbox>
	</object>
	<object>
		<name>checkbox</name>
		<pose>Unspecified</pose>
		<truncated>0</truncated>
		<difficult>0</difficult>
		<bndbox>
			<xmin>6</xmin>
			<ymin>53</ymin>
			<xmax>19</xmax>
			<ymax>63</ymax>
		</bndbox>
	</object>
	<object>
		<name>checkbox</name>
		<pose>Unspecified</pose>
		<truncated>0</truncated>
		<difficult>0</difficult>
		<bndbox>
			<xmin>109</xmin>
			<ymin>53</ymin>
			<xmax>121</xmax>
			<ymax>63</ymax>
		</bndbox>
	</object>
	<object>
		<name>textbox</name>
		<pose>Unspecified</pose>
		<truncated>0</truncated>
		<difficult>0</difficult>
		<bndbox>
			<xmin>2</xmin>
			<ymin>77</ymin>
			<xmax>210</xmax>
			<ymax>118</ymax>
		</bndbox>
	</object>
	<object>
		<name>textbox</name>
		<pose>Unspecified</pose>
		<truncated>0</truncated>
		<difficult>0</difficult>
		<bndbox>
			<xmin>205</xmin>
			<ymin>76</ymin>
			<xmax>413</xmax>
			<ymax>117</ymax>
		</bndbox>
	</object>
	<object>
		<name>textbox</name>
		<pose>Unspecified</pose>
		<truncated>0</truncated>
		<difficult>0</difficult>
		<bndbox>
			<xmin>205</xmin>
			<ymin>128</ymin>
			<xmax>413</xmax>
			<ymax>169</ymax>
		</bndbox>
	</object>
	<object>
		<name>textbox</name>
		<pose>Unspecified</pose>
		<truncated>1</truncated>
		<difficult>0</difficult>
		<bndbox>
			<xmin>1</xmin>
			<ymin>128</ymin>
			<xmax>209</xmax>
			<ymax>169</ymax>
		</bndbox>
	</object>
	<object>
		<name>textbox</name>
		<pose>Unspecified</pose>
		<truncated>1</truncated>
		<difficult>0</difficult>
		<bndbox>
			<xmin>1</xmin>
			<ymin>113</ymin>
			<xmax>210</xmax>
			<ymax>133</ymax>
		</bndbox>
	</object>
	<object>
		<name>textbox</name>
		<pose>Unspecified</pose>
		<truncated>0</truncated>
		<difficult>0</difficult>
		<bndbox>
			<xmin>205</xmin>
			<ymin>112</ymin>
			<xmax>415</xmax>
			<ymax>132</ymax>
		</bndbox>
	</object>
	<object>
		<name>textbox</name>
		<pose>Unspecified</pose>
		<truncated>1</truncated>
		<difficult>0</difficult>
		<bndbox>
			<xmin>1</xmin>
			<ymin>164</ymin>
			<xmax>210</xmax>
			<ymax>184</ymax>
		</bndbox>
	</object>
	<object>
		<name>textbox</name>
		<pose>Unspecified</pose>
		<truncated>0</truncated>
		<difficult>0</difficult>
		<bndbox>
			<xmin>205</xmin>
			<ymin>164</ymin>
			<xmax>415</xmax>
			<ymax>184</ymax>
		</bndbox>
	</object>
</annotation>